shifter/__init__.py
shifter/__main__.py
shifter/cli.py
shifter/data/__init__.py
shifter/data/config.json
shifter/data/gost.service
shifter/data/haproxy.cfg
shifter/services/__init__.py
shifter/services/config.py
shifter/services/gost.py
shifter/services/haproxy.py
shifter/services/iptables.py
shifter/services/status.py
shifter/services/system_info.py
shifter/services/xray.py
shifter/web/__init__.py
shifter/web/app.py
shifter/web/routes.py
shifter/web/templates/base.html
shifter/web/templates/configure.html
shifter/web/templates/index.html
shifter_toolkit-0.1.2.dist-info/licenses/LICENSE
shifter_toolkit-0.1.2.dist-info/METADATA
shifter_toolkit-0.1.2.dist-info/WHEEL
shifter_toolkit-0.1.2.dist-info/entry_points.txt
shifter_toolkit-0.1.2.dist-info/top_level.txt
shifter_toolkit-0.1.2.dist-info/RECORD
