Metadata-Version: 2.4
Name: shifter-toolkit
Version: 0.1.2
Summary: CLI toolkit for managing network tunnels and services with a web UI
Author: zZedix
License: MIT License
Project-URL: Homepage, https://github.com/zZedix/Shifter
Project-URL: Documentation, https://github.com/zZedix/Shifter#readme
Project-URL: Source, https://github.com/zZedix/Shifter
Project-URL: Issues, https://github.com/zZedix/Shifter/issues
Keywords: networking,tunneling,cli,aiohttp,automation
Classifier: Programming Language :: Python
Classifier: Programming Language :: Python :: 3.9
Classifier: Programming Language :: Python :: 3.10
Classifier: Programming Language :: Python :: 3.11
Classifier: License :: OSI Approved :: MIT License
Classifier: Operating System :: POSIX :: Linux
Classifier: Topic :: System :: Networking
Classifier: Topic :: System :: Systems Administration
Classifier: Environment :: Console
Requires-Python: >=3.9
License-File: LICENSE
Requires-Dist: aiohttp>=3.8
Requires-Dist: aiohttp-session[secure]>=2.11
Requires-Dist: aiohttp_jinja2>=1.5
Requires-Dist: click>=8.0
Requires-Dist: jinja2>=3.0
Requires-Dist: requests>=2.25
Dynamic: license-file
